translation_helper.py
android_localization_helper-0.1.4.dist-info/DESCRIPTION.rst
android_localization_helper-0.1.4.dist-info/entry_points.txt
android_localization_helper-0.1.4.dist-info/METADATA
android_localization_helper-0.1.4.dist-info/metadata.json
android_localization_helper-0.1.4.dist-info/namespace_packages.txt
android_localization_helper-0.1.4.dist-info/RECORD
android_localization_helper-0.1.4.dist-info/top_level.txt
android_localization_helper-0.1.4.dist-info/WHEEL
