Metadata-Version: 2.0
Name: android-localization-helper
Version: 0.1.4
Summary: Android localization helper
Home-page: https://github.com/jordanjoz1/android-localization-helper
Author: Jordan Jozwiak
Author-email: support@jozapps.com
License: MIT
Keywords: android localization translation translate
Platform: UNKNOWN
Classifier: License :: OSI Approved :: BSD License
Classifier: Intended Audience :: Developers
Classifier: Programming Language :: Python
